myvalidator/Graph.py
myvalidator/JSON_Parser.py
myvalidator/Terminal.py
myvalidator/__init__.py
myvalidator/komponenta.py
myvalidator/validations.py
myvalidator/validations_collector.py
myvalidator/cli/__init__.py
graph_validations-0.2.dist-info/LICENSE.txt
graph_validations-0.2.dist-info/METADATA
graph_validations-0.2.dist-info/WHEEL
graph_validations-0.2.dist-info/entry_points.txt
graph_validations-0.2.dist-info/top_level.txt
graph_validations-0.2.dist-info/RECORD
