Metadata-Version: 2.1
Name: graph-validations
Version: 0.2
Summary: Validations And Transformations For Schematic Editor Simple Graphs
Author: Balsa Bulatovic
Author-email: baki.b.2k02@gmail.com
License: MIT
Keywords: schematic editor validations
License-File: LICENSE.txt
Requires-Dist: Click
Requires-Dist: Typhoon-HIL-API
